{
    "date": "2022-06-07",
    "primemover_id": "7008",
    "sub_activity": "travel_empty",
    "time": [
        "01:51:07",
        "02:38:55",
        "03:30:46",
        "04:23:02",
        "06:28:02",
        "08:01:36",
        "08:04:46",
        "08:49:17",
        "09:33:42",
        "10:25:22",
        "11:17:59",
        "11:19:43",
        "12:08:18",
        "13:58:01",
        "14:55:50",
        "15:45:02",
        "17:00:17",
        "20:09:39",
        "20:57:50",
        "22:01:42",
        "22:48:40",
        "23:51:10"
    ],
    "travel_empty": [
        "0.0",
        "0.0",
        "0.0",
        "0.0",
        "0.0",
        "0.0",
        "0.0",
        "0.0",
        "0.0",
        "0.0",
        "0.0",
        "0.0",
        "0.0",
        "0.0",
        "0.0",
        "0.0",
        "0.0",
        "0.0",
        "0.0",
        "0.0",
        "0.0",
        "0.0"
    ],
    "stopped_empty": [
        "26.17",
        "30.47",
        "31.23",
        "90.32",
        "24.67",
        "1.37",
        "21.03",
        "22.33",
        "27.4",
        "28.93",
        "0.42",
        "25.92",
        "32.24",
        "21.89",
        "23.72",
        "47.27",
        "46.38",
        "23.66",
        "38.27",
        "23.82",
        "30.9",
        "21.87"
    ],
    "loading": [
        "0.0",
        "0.0",
        "0.0",
        "0.0",
        "0.0",
        "0.0",
        "0.0",
        "0.0",
        "0.0",
        "0.0",
        "0.0",
        "0.0",
        "0.0",
        "0.0",
        "0.0",
        "0.0",
        "0.0",
        "0.0",
        "0.0",
        "0.0",
        "0.0",
        "0.0"
    ],
    "travel_loaded": [
        "0.0",
        "0.0",
        "0.0",
        "0.0",
        "0.0",
        "0.0",
        "0.0",
        "0.0",
        "0.0",
        "0.0",
        "0.0",
        "0.0",
        "0.0",
        "0.0",
        "0.0",
        "0.0",
        "0.0",
        "0.0",
        "0.0",
        "0.0",
        "0.0",
        "0.0"
    ],
    "stopped_loaded": [
        "19.37",
        "17.27",
        "18.47",
        "14.84",
        "32.25",
        "0.69",
        "20.94",
        "19.75",
        "23.07",
        "21.13",
        "0.0",
        "14.37",
        "21.33",
        "33.53",
        "23.16",
        "25.73",
        "58.78",
        "22.1",
        "23.32",
        "20.74",
        "29.25",
        "19.48"
    ],
    "dumping": [
        "2.26",
        "4.12",
        "2.57",
        "1.35",
        "2.78",
        "1.12",
        "2.55",
        "2.33",
        "1.2",
        "2.55",
        "1.32",
        "2.19",
        "2.2",
        "2.4",
        "2.31",
        "2.26",
        "57.76",
        "2.42",
        "2.29",
        "2.4",
        "2.35",
        "2.54"
    ],
    "nett_cycle_time": [
        "47.8",
        "51.85",
        "52.27",
        "106.51",
        "59.71",
        "3.17",
        "44.52",
        "44.42",
        "51.67",
        "52.62",
        "1.73",
        "42.46",
        "55.78",
        "57.82",
        "49.2",
        "75.25",
        "162.9",
        "48.18",
        "63.87",
        "46.97",
        "62.5",
        "43.88"
    ]
}